pyadio/__init__.py
pyadio/_adio.py
pyadio/adc.py
pyadio/pyadio.py
pyadio/utils.py
pyadio-0.1.0.dist-info/METADATA
pyadio-0.1.0.dist-info/WHEEL
pyadio-0.1.0.dist-info/entry_points.txt
pyadio-0.1.0.dist-info/licenses/LICENCE.txt
pyadio-0.1.0.dist-info/RECORD
