Metadata-Version: 2.4
Name: pyadio
Version: 0.1.0
Summary: Add your description here
Author-email: takumi-nishimura <clp13218@nitech.jp>
License-Expression: MIT
License-File: LICENCE.txt
Classifier: License :: OSI Approved :: MIT License
Classifier: Programming Language :: Python :: 3
Requires-Python: >=3.9
Requires-Dist: pydantic>=2.10.4
Requires-Dist: pyserial>=3.5
